mypackage_takipipo/__init__.py
mypackage_takipipo/module.py
mypackage_takipipo-0.0.1.dist-info/METADATA
mypackage_takipipo-0.0.1.dist-info/WHEEL
mypackage_takipipo-0.0.1.dist-info/top_level.txt
mypackage_takipipo-0.0.1.dist-info/RECORD
